veg/__init__.py
veg-0.0.0.dist-info/METADATA
veg-0.0.0.dist-info/WHEEL
veg-0.0.0.dist-info/top_level.txt
veg-0.0.0.dist-info/RECORD
