Metadata-Version: 2.1
Name: veg
Version: 0.0.0
Summary: yaaaaaaaaaa
Author-email: Ilan Gold <ilanbassgold@gmail.com>
